AUTHORS
CHANGELOG
COPYING
MANIFEST.in
README.rst
setup.cfg
setup.py
capilogs/__init__.py
capilogs/_version.py
capilogs/bin.py
capilogs/core.py
capilogs/exceptions.py
capilogs/keys.py
capilogs.egg-info/PKG-INFO
capilogs.egg-info/SOURCES.txt
capilogs.egg-info/dependency_links.txt
capilogs.egg-info/entry_points.txt
capilogs.egg-info/not-zip-safe
capilogs.egg-info/requires.txt
capilogs.egg-info/top_level.txt
inst/__init__.py
inst/instrumenter.py