Metadata-Version: 1.1
Name: capilogs
Version: 0.11.8
Summary: Easy correlated logging and debugging for Amazon API Gateway and AWS Lambda Serverless APIs
Home-page: http://github.com/yoramk2/capilogs
Author: Yoram Kochol
Author-email: yoramk2@yahoo.com
License: BSD
Keywords: aws logs cloudwatch api gateway lambda serverless logging
Platform: any
Classifier: Programming Language :: Python :: 3
Classifier: Programming Language :: Python :: 2
Classifier: Development Status :: 4 - Beta
Classifier: Environment :: Web Environment
Classifier: Intended Audience :: Developers
Classifier: License :: OSI Approved :: BSD License
Classifier: Operating System :: OS Independent
Classifier: Topic :: Utilities
